{
  "system": "sonar",
  "version": "1.0.0",
  "generatedAt": "2026-06-28T12:11:51.729459+02:00",
  "status": {
    "current": "operational",
    "isHealthy": true,
    "hasErrors": false,
    "errorMessages": []
  },
  "notification": {
    "title": "✅ Skan 12:08 — +4 nowe / -7 znikły",
    "body": "Pojawiło się 4 nowych, znikło 7 ofert mieszkań w Lublinie"
  },
  "lastScan": {
    "id": "2026-06-28T12-08-45",
    "timestamp": "2026-06-28T12:08:45.823458+02:00",
    "endTimestamp": "2026-06-28T12:10:55.708423+02:00",
    "durationSeconds": 129.88,
    "durationFormatted": "2m 9s",
    "uiStatus": "success",
    "rawStatus": "completed",
    "scanTimeFormatted": "12:08",
    "failureReason": null,
    "notification": {
      "title": "✅ Skan 12:08 — +4 nowe / -7 znikły",
      "body": "Pojawiło się 4 nowych, znikło 7 ofert mieszkań w Lublinie"
    },
    "offers": {
      "found": 617,
      "processed": 533,
      "new": 4,
      "disappeared": 7,
      "updated": 529,
      "active": 576,
      "inactive": 1149
    },
    "skipped": {
      "noAddress": 27,
      "noCoords": 1,
      "duplicates": 55
    },
    "errors": [],
    "hasErrors": false
  },
  "recentScans": [
    {
      "id": "2026-06-28T12-08-45",
      "scanTimeFormatted": "12:08",
      "uiStatus": "success",
      "newOffers": 4,
      "disappearedOffers": 7,
      "hasErrors": false
    },
    {
      "id": "2026-06-28T08-38-41",
      "scanTimeFormatted": "08:38",
      "uiStatus": "success",
      "newOffers": 1,
      "disappearedOffers": 3,
      "hasErrors": false
    },
    {
      "id": "2026-06-27T22-34-02",
      "scanTimeFormatted": "22:34",
      "uiStatus": "success",
      "newOffers": 9,
      "disappearedOffers": 7,
      "hasErrors": false
    },
    {
      "id": "2026-06-27T16-56-32",
      "scanTimeFormatted": "16:56",
      "uiStatus": "success",
      "newOffers": 3,
      "disappearedOffers": 7,
      "hasErrors": false
    },
    {
      "id": "2026-06-27T11-35-15",
      "scanTimeFormatted": "11:35",
      "uiStatus": "success",
      "newOffers": 1,
      "disappearedOffers": 8,
      "hasErrors": false
    },
    {
      "id": "2026-06-27T07-40-00",
      "scanTimeFormatted": "07:40",
      "uiStatus": "success",
      "newOffers": 2,
      "disappearedOffers": 1,
      "hasErrors": false
    }
  ],
  "schedule": {
    "times": [
      "09:17",
      "15:17",
      "21:17"
    ],
    "timezone": "Europe/Warsaw",
    "nextScanAt": "2026-06-28T15:17:00+02:00"
  },
  "statistics": {
    "totalScans": 100,
    "successRate": 100.0,
    "avgDurationSeconds": 123.44,
    "avgOffersFound": 528.1
  }
}